aoc_tool/__init__.py
aoc_tool-0.0.5.dist-info/LICENSE
aoc_tool-0.0.5.dist-info/METADATA
aoc_tool-0.0.5.dist-info/WHEEL
aoc_tool-0.0.5.dist-info/top_level.txt
aoc_tool-0.0.5.dist-info/RECORD
